<?xml version="1.0" encoding="utf-8" ?>
<c2layout>
    <name>Level 3</name>
    <sid>977185993425236</sid>
    <event-sheet>Event sheet 1</event-sheet>
    <size>
        <width>1695</width>
        <height>960</height>
    </size>
    <margins>
        <horizontal>500</horizontal>
        <vertical>500</vertical>
    </margins>
    <unbounded-scrolling>0</unbounded-scrolling>
    <layers>
        <layer name="Layer 0" sid="406897892500204">
            <initially-visible>1</initially-visible>
            <background-color>255,255,255</background-color>
            <transparent>0</transparent>
            <parallax>
                <x>1</x>
                <y>1</y>
            </parallax>
            <zoom-rate>1</zoom-rate>
            <opacity>1</opacity>
            <force-own-texture>0</force-own-texture>
            <global>0</global>
            <use-render-cells>0</use-render-cells>
            <blend-mode>0</blend-mode>
            <effect-fallback>0</effect-fallback>
            <instances>
                <instance type="EnemyPath2" uid="68">
                    <properties>
                        <initial-visibility>Invisible</initial-visibility>
                        <initial-animation>Default</initial-animation>
                        <initial-frame>0</initial-frame>
                        <collisions>Enabled</collisions>
                    </properties>
                    <instance-variables>
                        <Variable1>1</Variable1>
                    </instance-variables>
                    <blend-mode>0</blend-mode>
                    <effect-fallback>0</effect-fallback>
                    <world>
                        <x>1186</x>
                        <y>820</y>
                        <z>0</z>
                        <width>32</width>
                        <height>32</height>
                        <depth>0</depth>
                        <hotspotX>0.5</hotspotX>
                        <hotspotY>0.5</hotspotY>
                        <angle>0</angle>
                        <opacity>1</opacity>
                    </world>
                </instance>
                <instance type="EnemyPath2" uid="69">
                    <properties>
                        <initial-visibility>Invisible</initial-visibility>
                        <initial-animation>Default</initial-animation>
                        <initial-frame>0</initial-frame>
                        <collisions>Enabled</collisions>
                    </properties>
                    <instance-variables>
                        <Variable1>2</Variable1>
                    </instance-variables>
                    <blend-mode>0</blend-mode>
                    <effect-fallback>0</effect-fallback>
                    <world>
                        <x>1382</x>
                        <y>875</y>
                        <z>0</z>
                        <width>32</width>
                        <height>32</height>
                        <depth>0</depth>
                        <hotspotX>0.5</hotspotX>
                        <hotspotY>0.5</hotspotY>
                        <angle>0</angle>
                        <opacity>1</opacity>
                    </world>
                </instance>
                <instance type="EnemyPath2" uid="70">
                    <properties>
                        <initial-visibility>Invisible</initial-visibility>
                        <initial-animation>Default</initial-animation>
                        <initial-frame>0</initial-frame>
                        <collisions>Enabled</collisions>
                    </properties>
                    <instance-variables>
                        <Variable1>3</Variable1>
                    </instance-variables>
                    <blend-mode>0</blend-mode>
                    <effect-fallback>0</effect-fallback>
                    <world>
                        <x>1585</x>
                        <y>835</y>
                        <z>0</z>
                        <width>32</width>
                        <height>32</height>
                        <depth>0</depth>
                        <hotspotX>0.5</hotspotX>
                        <hotspotY>0.5</hotspotY>
                        <angle>0</angle>
                        <opacity>1</opacity>
                    </world>
                </instance>
                <instance type="EnemyPath2" uid="71">
                    <properties>
                        <initial-visibility>Invisible</initial-visibility>
                        <initial-animation>Default</initial-animation>
                        <initial-frame>0</initial-frame>
                        <collisions>Enabled</collisions>
                    </properties>
                    <instance-variables>
                        <Variable1>4</Variable1>
                    </instance-variables>
                    <blend-mode>0</blend-mode>
                    <effect-fallback>0</effect-fallback>
                    <world>
                        <x>1642</x>
                        <y>603</y>
                        <z>0</z>
                        <width>32</width>
                        <height>32</height>
                        <depth>0</depth>
                        <hotspotX>0.5</hotspotX>
                        <hotspotY>0.5</hotspotY>
                        <angle>0</angle>
                        <opacity>1</opacity>
                    </world>
                </instance>
                <instance type="EnemyPath2" uid="72">
                    <properties>
                        <initial-visibility>Invisible</initial-visibility>
                        <initial-animation>Default</initial-animation>
                        <initial-frame>0</initial-frame>
                        <collisions>Enabled</collisions>
                    </properties>
                    <instance-variables>
                        <Variable1>5</Variable1>
                    </instance-variables>
                    <blend-mode>0</blend-mode>
                    <effect-fallback>0</effect-fallback>
                    <world>
                        <x>1534</x>
                        <y>509</y>
                        <z>0</z>
                        <width>32</width>
                        <height>32</height>
                        <depth>0</depth>
                        <hotspotX>0.5</hotspotX>
                        <hotspotY>0.5</hotspotY>
                        <angle>0</angle>
                        <opacity>1</opacity>
                    </world>
                </instance>
                <instance type="EnemyPath2" uid="73">
                    <properties>
                        <initial-visibility>Invisible</initial-visibility>
                        <initial-animation>Default</initial-animation>
                        <initial-frame>0</initial-frame>
                        <collisions>Enabled</collisions>
                    </properties>
                    <instance-variables>
                        <Variable1>6</Variable1>
                    </instance-variables>
                    <blend-mode>0</blend-mode>
                    <effect-fallback>0</effect-fallback>
                    <world>
                        <x>1435</x>
                        <y>758</y>
                        <z>0</z>
                        <width>32</width>
                        <height>32</height>
                        <depth>0</depth>
                        <hotspotX>0.5</hotspotX>
                        <hotspotY>0.5</hotspotY>
                        <angle>0</angle>
                        <opacity>1</opacity>
                    </world>
                </instance>
                <instance type="EnemyPath2" uid="74">
                    <properties>
                        <initial-visibility>Invisible</initial-visibility>
                        <initial-animation>Default</initial-animation>
                        <initial-frame>0</initial-frame>
                        <collisions>Enabled</collisions>
                    </properties>
                    <instance-variables>
                        <Variable1>7</Variable1>
                    </instance-variables>
                    <blend-mode>0</blend-mode>
                    <effect-fallback>0</effect-fallback>
                    <world>
                        <x>1297</x>
                        <y>508</y>
                        <z>0</z>
                        <width>32</width>
                        <height>32</height>
                        <depth>0</depth>
                        <hotspotX>0.5</hotspotX>
                        <hotspotY>0.5</hotspotY>
                        <angle>0</angle>
                        <opacity>1</opacity>
                    </world>
                </instance>
                <instance type="EnemyPath2" uid="75">
                    <properties>
                        <initial-visibility>Invisible</initial-visibility>
                        <initial-animation>Default</initial-animation>
                        <initial-frame>0</initial-frame>
                        <collisions>Enabled</collisions>
                    </properties>
                    <instance-variables>
                        <Variable1>8</Variable1>
                    </instance-variables>
                    <blend-mode>0</blend-mode>
                    <effect-fallback>0</effect-fallback>
                    <world>
                        <x>1552</x>
                        <y>349</y>
                        <z>0</z>
                        <width>32</width>
                        <height>32</height>
                        <depth>0</depth>
                        <hotspotX>0.5</hotspotX>
                        <hotspotY>0.5</hotspotY>
                        <angle>0</angle>
                        <opacity>1</opacity>
                    </world>
                </instance>
                <instance type="EnemyPath2" uid="76">
                    <properties>
                        <initial-visibility>Invisible</initial-visibility>
                        <initial-animation>Default</initial-animation>
                        <initial-frame>0</initial-frame>
                        <collisions>Enabled</collisions>
                    </properties>
                    <instance-variables>
                        <Variable1>9</Variable1>
                    </instance-variables>
                    <blend-mode>0</blend-mode>
                    <effect-fallback>0</effect-fallback>
                    <world>
                        <x>1313</x>
                        <y>215</y>
                        <z>0</z>
                        <width>32</width>
                        <height>32</height>
                        <depth>0</depth>
                        <hotspotX>0.5</hotspotX>
                        <hotspotY>0.5</hotspotY>
                        <angle>0</angle>
                        <opacity>1</opacity>
                    </world>
                </instance>
                <instance type="EnemyPath3" uid="86">
                    <properties>
                        <initial-visibility>Invisible</initial-visibility>
                        <initial-animation>Default</initial-animation>
                        <initial-frame>0</initial-frame>
                        <collisions>Enabled</collisions>
                    </properties>
                    <instance-variables>
                        <Variable1>1</Variable1>
                    </instance-variables>
                    <blend-mode>0</blend-mode>
                    <effect-fallback>0</effect-fallback>
                    <world>
                        <x>315</x>
                        <y>288</y>
                        <z>0</z>
                        <width>32</width>
                        <height>32</height>
                        <depth>0</depth>
                        <hotspotX>0.5</hotspotX>
                        <hotspotY>0.5</hotspotY>
                        <angle>0</angle>
                        <opacity>1</opacity>
                    </world>
                </instance>
                <instance type="EnemyPath3" uid="87">
                    <properties>
                        <initial-visibility>Invisible</initial-visibility>
                        <initial-animation>Default</initial-animation>
                        <initial-frame>0</initial-frame>
                        <collisions>Enabled</collisions>
                    </properties>
                    <instance-variables>
                        <Variable1>2</Variable1>
                    </instance-variables>
                    <blend-mode>0</blend-mode>
                    <effect-fallback>0</effect-fallback>
                    <world>
                        <x>252</x>
                        <y>95</y>
                        <z>0</z>
                        <width>32</width>
                        <height>32</height>
                        <depth>0</depth>
                        <hotspotX>0.5</hotspotX>
                        <hotspotY>0.5</hotspotY>
                        <angle>0</angle>
                        <opacity>1</opacity>
                    </world>
                </instance>
                <instance type="EnemyPath3" uid="90">
                    <properties>
                        <initial-visibility>Invisible</initial-visibility>
                        <initial-animation>Default</initial-animation>
                        <initial-frame>0</initial-frame>
                        <collisions>Enabled</collisions>
                    </properties>
                    <instance-variables>
                        <Variable1>3</Variable1>
                    </instance-variables>
                    <blend-mode>0</blend-mode>
                    <effect-fallback>0</effect-fallback>
                    <world>
                        <x>96</x>
                        <y>104</y>
                        <z>0</z>
                        <width>32</width>
                        <height>32</height>
                        <depth>0</depth>
                        <hotspotX>0.5</hotspotX>
                        <hotspotY>0.5</hotspotY>
                        <angle>0</angle>
                        <opacity>1</opacity>
                    </world>
                </instance>
                <instance type="EnemyPath3" uid="91">
                    <properties>
                        <initial-visibility>Invisible</initial-visibility>
                        <initial-animation>Default</initial-animation>
                        <initial-frame>0</initial-frame>
                        <collisions>Enabled</collisions>
                    </properties>
                    <instance-variables>
                        <Variable1>4</Variable1>
                    </instance-variables>
                    <blend-mode>0</blend-mode>
                    <effect-fallback>0</effect-fallback>
                    <world>
                        <x>73</x>
                        <y>524</y>
                        <z>0</z>
                        <width>32</width>
                        <height>32</height>
                        <depth>0</depth>
                        <hotspotX>0.5</hotspotX>
                        <hotspotY>0.5</hotspotY>
                        <angle>0</angle>
                        <opacity>1</opacity>
                    </world>
                </instance>
                <instance type="EnemyPath3" uid="93">
                    <properties>
                        <initial-visibility>Invisible</initial-visibility>
                        <initial-animation>Default</initial-animation>
                        <initial-frame>0</initial-frame>
                        <collisions>Enabled</collisions>
                    </properties>
                    <instance-variables>
                        <Variable1>5</Variable1>
                    </instance-variables>
                    <blend-mode>0</blend-mode>
                    <effect-fallback>0</effect-fallback>
                    <world>
                        <x>301</x>
                        <y>613</y>
                        <z>0</z>
                        <width>32</width>
                        <height>32</height>
                        <depth>0</depth>
                        <hotspotX>0.5</hotspotX>
                        <hotspotY>0.5</hotspotY>
                        <angle>0</angle>
                        <opacity>1</opacity>
                    </world>
                </instance>
                <instance type="EnemyPath5" uid="80">
                    <properties>
                        <initial-visibility>Invisible</initial-visibility>
                        <initial-animation>Default</initial-animation>
                        <initial-frame>0</initial-frame>
                        <collisions>Enabled</collisions>
                    </properties>
                    <instance-variables>
                        <Variable1>1</Variable1>
                    </instance-variables>
                    <blend-mode>0</blend-mode>
                    <effect-fallback>0</effect-fallback>
                    <world>
                        <x>862</x>
                        <y>72</y>
                        <z>0</z>
                        <width>32</width>
                        <height>32</height>
                        <depth>0</depth>
                        <hotspotX>0.5</hotspotX>
                        <hotspotY>0.5</hotspotY>
                        <angle>0</angle>
                        <opacity>1</opacity>
                    </world>
                </instance>
                <instance type="EnemyPath5" uid="81">
                    <properties>
                        <initial-visibility>Invisible</initial-visibility>
                        <initial-animation>Default</initial-animation>
                        <initial-frame>0</initial-frame>
                        <collisions>Enabled</collisions>
                    </properties>
                    <instance-variables>
                        <Variable1>2</Variable1>
                    </instance-variables>
                    <blend-mode>0</blend-mode>
                    <effect-fallback>0</effect-fallback>
                    <world>
                        <x>1125</x>
                        <y>137</y>
                        <z>0</z>
                        <width>32</width>
                        <height>32</height>
                        <depth>0</depth>
                        <hotspotX>0.5</hotspotX>
                        <hotspotY>0.5</hotspotY>
                        <angle>0</angle>
                        <opacity>1</opacity>
                    </world>
                </instance>
                <instance type="EnemyPath5" uid="89">
                    <properties>
                        <initial-visibility>Invisible</initial-visibility>
                        <initial-animation>Default</initial-animation>
                        <initial-frame>0</initial-frame>
                        <collisions>Enabled</collisions>
                    </properties>
                    <instance-variables>
                        <Variable1>3</Variable1>
                    </instance-variables>
                    <blend-mode>0</blend-mode>
                    <effect-fallback>0</effect-fallback>
                    <world>
                        <x>1426</x>
                        <y>92</y>
                        <z>0</z>
                        <width>32</width>
                        <height>32</height>
                        <depth>0</depth>
                        <hotspotX>0.5</hotspotX>
                        <hotspotY>0.5</hotspotY>
                        <angle>0</angle>
                        <opacity>1</opacity>
                    </world>
                </instance>
                <instance type="EnemyPath6" uid="59">
                    <properties>
                        <initial-visibility>Invisible</initial-visibility>
                        <initial-animation>Default</initial-animation>
                        <initial-frame>0</initial-frame>
                        <collisions>Enabled</collisions>
                    </properties>
                    <instance-variables>
                        <Variable1>1</Variable1>
                    </instance-variables>
                    <blend-mode>0</blend-mode>
                    <effect-fallback>0</effect-fallback>
                    <world>
                        <x>416</x>
                        <y>488</y>
                        <z>0</z>
                        <width>32</width>
                        <height>32</height>
                        <depth>0</depth>
                        <hotspotX>0.5</hotspotX>
                        <hotspotY>0.5</hotspotY>
                        <angle>0</angle>
                        <opacity>1</opacity>
                    </world>
                </instance>
                <instance type="EnemyPath6" uid="78">
                    <properties>
                        <initial-visibility>Invisible</initial-visibility>
                        <initial-animation>Default</initial-animation>
                        <initial-frame>0</initial-frame>
                        <collisions>Enabled</collisions>
                    </properties>
                    <instance-variables>
                        <Variable1>2</Variable1>
                    </instance-variables>
                    <blend-mode>0</blend-mode>
                    <effect-fallback>0</effect-fallback>
                    <world>
                        <x>818</x>
                        <y>365</y>
                        <z>0</z>
                        <width>32</width>
                        <height>32</height>
                        <depth>0</depth>
                        <hotspotX>0.5</hotspotX>
                        <hotspotY>0.5</hotspotY>
                        <angle>0</angle>
                        <opacity>1</opacity>
                    </world>
                </instance>
                <instance type="EnemyPath6" uid="82">
                    <properties>
                        <initial-visibility>Invisible</initial-visibility>
                        <initial-animation>Default</initial-animation>
                        <initial-frame>0</initial-frame>
                        <collisions>Enabled</collisions>
                    </properties>
                    <instance-variables>
                        <Variable1>3</Variable1>
                    </instance-variables>
                    <blend-mode>0</blend-mode>
                    <effect-fallback>0</effect-fallback>
                    <world>
                        <x>505</x>
                        <y>103</y>
                        <z>0</z>
                        <width>32</width>
                        <height>32</height>
                        <depth>0</depth>
                        <hotspotX>0.5</hotspotX>
                        <hotspotY>0.5</hotspotY>
                        <angle>0</angle>
                        <opacity>1</opacity>
                    </world>
                </instance>
                <instance type="EnemyPath4" uid="83">
                    <properties>
                        <initial-visibility>Invisible</initial-visibility>
                        <initial-animation>Default</initial-animation>
                        <initial-frame>0</initial-frame>
                        <collisions>Enabled</collisions>
                    </properties>
                    <instance-variables>
                        <Variable1>1</Variable1>
                    </instance-variables>
                    <blend-mode>0</blend-mode>
                    <effect-fallback>0</effect-fallback>
                    <world>
                        <x>780</x>
                        <y>242</y>
                        <z>0</z>
                        <width>32</width>
                        <height>32</height>
                        <depth>0</depth>
                        <hotspotX>0.5</hotspotX>
                        <hotspotY>0.5</hotspotY>
                        <angle>0</angle>
                        <opacity>1</opacity>
                    </world>
                </instance>
                <instance type="EnemyPath4" uid="84">
                    <properties>
                        <initial-visibility>Invisible</initial-visibility>
                        <initial-animation>Default</initial-animation>
                        <initial-frame>0</initial-frame>
                        <collisions>Enabled</collisions>
                    </properties>
                    <instance-variables>
                        <Variable1>2</Variable1>
                    </instance-variables>
                    <blend-mode>0</blend-mode>
                    <effect-fallback>0</effect-fallback>
                    <world>
                        <x>978</x>
                        <y>242</y>
                        <z>0</z>
                        <width>32</width>
                        <height>32</height>
                        <depth>0</depth>
                        <hotspotX>0.5</hotspotX>
                        <hotspotY>0.5</hotspotY>
                        <angle>0</angle>
                        <opacity>1</opacity>
                    </world>
                </instance>
                <instance type="EnemyPath4" uid="79">
                    <properties>
                        <initial-visibility>Invisible</initial-visibility>
                        <initial-animation>Default</initial-animation>
                        <initial-frame>0</initial-frame>
                        <collisions>Enabled</collisions>
                    </properties>
                    <instance-variables>
                        <Variable1>3</Variable1>
                    </instance-variables>
                    <blend-mode>0</blend-mode>
                    <effect-fallback>0</effect-fallback>
                    <world>
                        <x>983</x>
                        <y>493</y>
                        <z>0</z>
                        <width>32</width>
                        <height>32</height>
                        <depth>0</depth>
                        <hotspotX>0.5</hotspotX>
                        <hotspotY>0.5</hotspotY>
                        <angle>0</angle>
                        <opacity>1</opacity>
                    </world>
                </instance>
                <instance type="EnemyPath1" uid="32">
                    <properties>
                        <initial-visibility>Invisible</initial-visibility>
                        <initial-animation>Default</initial-animation>
                        <initial-frame>0</initial-frame>
                        <collisions>Enabled</collisions>
                    </properties>
                    <instance-variables>
                        <Variable1>1</Variable1>
                    </instance-variables>
                    <blend-mode>0</blend-mode>
                    <effect-fallback>0</effect-fallback>
                    <world>
                        <x>638.312194824</x>
                        <y>823.430480957</y>
                        <z>0</z>
                        <width>32</width>
                        <height>32</height>
                        <depth>0</depth>
                        <hotspotX>0.5</hotspotX>
                        <hotspotY>0.5</hotspotY>
                        <angle>0</angle>
                        <opacity>1</opacity>
                    </world>
                </instance>
                <instance type="EnemyPath1" uid="65">
                    <properties>
                        <initial-visibility>Invisible</initial-visibility>
                        <initial-animation>Default</initial-animation>
                        <initial-frame>0</initial-frame>
                        <collisions>Enabled</collisions>
                    </properties>
                    <instance-variables>
                        <Variable1>4</Variable1>
                    </instance-variables>
                    <blend-mode>0</blend-mode>
                    <effect-fallback>0</effect-fallback>
                    <world>
                        <x>823.90838623</x>
                        <y>898.353088379</y>
                        <z>0</z>
                        <width>32</width>
                        <height>32</height>
                        <depth>0</depth>
                        <hotspotX>0.5</hotspotX>
                        <hotspotY>0.5</hotspotY>
                        <angle>0</angle>
                        <opacity>1</opacity>
                    </world>
                </instance>
                <instance type="EnemyPath1" uid="66">
                    <properties>
                        <initial-visibility>Invisible</initial-visibility>
                        <initial-animation>Default</initial-animation>
                        <initial-frame>0</initial-frame>
                        <collisions>Enabled</collisions>
                    </properties>
                    <instance-variables>
                        <Variable1>3</Variable1>
                    </instance-variables>
                    <blend-mode>0</blend-mode>
                    <effect-fallback>0</effect-fallback>
                    <world>
                        <x>947.589538574</x>
                        <y>806.116516113</y>
                        <z>0</z>
                        <width>32</width>
                        <height>32</height>
                        <depth>0</depth>
                        <hotspotX>0.5</hotspotX>
                        <hotspotY>0.5</hotspotY>
                        <angle>0</angle>
                        <opacity>1</opacity>
                    </world>
                </instance>
                <instance type="EnemyPath1" uid="67">
                    <properties>
                        <initial-visibility>Invisible</initial-visibility>
                        <initial-animation>Default</initial-animation>
                        <initial-frame>0</initial-frame>
                        <collisions>Enabled</collisions>
                    </properties>
                    <instance-variables>
                        <Variable1>2</Variable1>
                    </instance-variables>
                    <blend-mode>0</blend-mode>
                    <effect-fallback>0</effect-fallback>
                    <world>
                        <x>763.510375977</x>
                        <y>692.918395996</y>
                        <z>0</z>
                        <width>32</width>
                        <height>32</height>
                        <depth>0</depth>
                        <hotspotX>0.5</hotspotX>
                        <hotspotY>0.5</hotspotY>
                        <angle>0</angle>
                        <opacity>1</opacity>
                    </world>
                </instance>
            </instances>
            <effects />
        </layer>
        <layer name="Game" sid="263727612917602">
            <initially-visible>1</initially-visible>
            <background-color>255,255,255</background-color>
            <transparent>1</transparent>
            <parallax>
                <x>1</x>
                <y>1</y>
            </parallax>
            <zoom-rate>1</zoom-rate>
            <opacity>1</opacity>
            <force-own-texture>0</force-own-texture>
            <global>0</global>
            <use-render-cells>0</use-render-cells>
            <blend-mode>0</blend-mode>
            <effect-fallback>0</effect-fallback>
            <instances>
                <instance type="Jail" uid="61">
                    <properties>
                        <initial-visibility>Visible</initial-visibility>
                        <initial-animation>Default</initial-animation>
                        <initial-frame>0</initial-frame>
                        <collisions>Enabled</collisions>
                    </properties>
                    <blend-mode>0</blend-mode>
                    <effect-fallback>0</effect-fallback>
                    <world>
                        <x>492</x>
                        <y>857</y>
                        <z>0</z>
                        <width>32</width>
                        <height>32</height>
                        <depth>0</depth>
                        <hotspotX>0.5</hotspotX>
                        <hotspotY>0.5</hotspotY>
                        <angle>0</angle>
                        <opacity>1</opacity>
                    </world>
                </instance>
                <instance type="Player" uid="62">
                    <properties>
                        <initial-visibility>Visible</initial-visibility>
                        <initial-animation>Default</initial-animation>
                        <initial-frame>0</initial-frame>
                        <collisions>Enabled</collisions>
                    </properties>
                    <behavior-instances>
                        <behavior-instance type="8Direction">
                            <properties>
                                <max-speed>200</max-speed>
                                <acceleration>600</acceleration>
                                <deceleration>1000</deceleration>
                                <directions>8 directions</directions>
                                <set-angle>No</set-angle>
                                <default-controls>Yes</default-controls>
                                <initial-state>Enabled</initial-state>
                            </properties>
                        </behavior-instance>
                        <behavior-instance type="ScrollTo">
                            <properties>
                                <initial-state>Enabled</initial-state>
                            </properties>
                        </behavior-instance>
                        <behavior-instance type="LineOfSight">
                            <properties>
                                <obstacles>Solids</obstacles>
                                <range>10000</range>
                                <cone-of-view>360</cone-of-view>
                                <use-collision-cells>Yes</use-collision-cells>
                            </properties>
                        </behavior-instance>
                    </behavior-instances>
                    <blend-mode>0</blend-mode>
                    <effect-fallback>0</effect-fallback>
                    <world>
                        <x>497</x>
                        <y>857</y>
                        <z>0</z>
                        <width>32</width>
                        <height>32</height>
                        <depth>0</depth>
                        <hotspotX>0.46875</hotspotX>
                        <hotspotY>0.59375</hotspotY>
                        <angle>0.000014532</angle>
                        <opacity>1</opacity>
                    </world>
                </instance>
                <instance type="Enemy" uid="64">
                    <properties>
                        <initial-visibility>Visible</initial-visibility>
                        <initial-animation>Default</initial-animation>
                        <initial-frame>0</initial-frame>
                        <collisions>Enabled</collisions>
                    </properties>
                    <instance-variables>
                        <StepNum>1</StepNum>
                        <Alerted>false</Alerted>
                        <alertCooldown>0</alertCooldown>
                        <hasLineOfSight>false</hasLineOfSight>
                    </instance-variables>
                    <behavior-instances>
                        <behavior-instance type="LineOfSight">
                            <properties>
                                <obstacles>Solids</obstacles>
                                <range>200</range>
                                <cone-of-view>30</cone-of-view>
                                <use-collision-cells>Yes</use-collision-cells>
                            </properties>
                        </behavior-instance>
                        <behavior-instance type="Solid">
                            <properties>
                                <initial-state>Enabled</initial-state>
                            </properties>
                        </behavior-instance>
                        <behavior-instance type="Pathfinding">
                            <properties>
                                <cell-size>16</cell-size>
                                <cell-border>0</cell-border>
                                <obstacles>Solids</obstacles>
                                <max-speed>300</max-speed>
                                <acceleration>1000</acceleration>
                                <deceleration>2000</deceleration>
                                <rotate-speed>135</rotate-speed>
                                <rotate-object>No</rotate-object>
                                <diagonals>Enabled</diagonals>
                                <initial-state>Enabled</initial-state>
                            </properties>
                        </behavior-instance>
                        <behavior-instance type="Flash" />
                    </behavior-instances>
                    <blend-mode>0</blend-mode>
                    <effect-fallback>0</effect-fallback>
                    <world>
                        <x>653</x>
                        <y>818</y>
                        <z>0</z>
                        <width>32</width>
                        <height>32</height>
                        <depth>0</depth>
                        <hotspotX>0.5</hotspotX>
                        <hotspotY>0.5</hotspotY>
                        <angle>0</angle>
                        <opacity>1</opacity>
                    </world>
                </instance>
                <instance type="Enemy" uid="77">
                    <properties>
                        <initial-visibility>Visible</initial-visibility>
                        <initial-animation>Default</initial-animation>
                        <initial-frame>0</initial-frame>
                        <collisions>Enabled</collisions>
                    </properties>
                    <instance-variables>
                        <StepNum>1</StepNum>
                        <Alerted>false</Alerted>
                        <alertCooldown>0</alertCooldown>
                        <hasLineOfSight>false</hasLineOfSight>
                    </instance-variables>
                    <behavior-instances>
                        <behavior-instance type="LineOfSight">
                            <properties>
                                <obstacles>Solids</obstacles>
                                <range>200</range>
                                <cone-of-view>30</cone-of-view>
                                <use-collision-cells>Yes</use-collision-cells>
                            </properties>
                        </behavior-instance>
                        <behavior-instance type="Solid">
                            <properties>
                                <initial-state>Enabled</initial-state>
                            </properties>
                        </behavior-instance>
                        <behavior-instance type="Pathfinding">
                            <properties>
                                <cell-size>16</cell-size>
                                <cell-border>0</cell-border>
                                <obstacles>Solids</obstacles>
                                <max-speed>300</max-speed>
                                <acceleration>1000</acceleration>
                                <deceleration>2000</deceleration>
                                <rotate-speed>135</rotate-speed>
                                <rotate-object>No</rotate-object>
                                <diagonals>Enabled</diagonals>
                                <initial-state>Enabled</initial-state>
                            </properties>
                        </behavior-instance>
                        <behavior-instance type="Flash" />
                    </behavior-instances>
                    <blend-mode>0</blend-mode>
                    <effect-fallback>0</effect-fallback>
                    <world>
                        <x>1193</x>
                        <y>825</y>
                        <z>0</z>
                        <width>32</width>
                        <height>32</height>
                        <depth>0</depth>
                        <hotspotX>0.5</hotspotX>
                        <hotspotY>0.5</hotspotY>
                        <angle>0</angle>
                        <opacity>1</opacity>
                    </world>
                </instance>
                <instance type="Enemy" uid="85">
                    <properties>
                        <initial-visibility>Visible</initial-visibility>
                        <initial-animation>Default</initial-animation>
                        <initial-frame>0</initial-frame>
                        <collisions>Enabled</collisions>
                    </properties>
                    <instance-variables>
                        <StepNum>1</StepNum>
                        <Alerted>false</Alerted>
                        <alertCooldown>0</alertCooldown>
                        <hasLineOfSight>false</hasLineOfSight>
                    </instance-variables>
                    <behavior-instances>
                        <behavior-instance type="LineOfSight">
                            <properties>
                                <obstacles>Solids</obstacles>
                                <range>200</range>
                                <cone-of-view>30</cone-of-view>
                                <use-collision-cells>Yes</use-collision-cells>
                            </properties>
                        </behavior-instance>
                        <behavior-instance type="Solid">
                            <properties>
                                <initial-state>Enabled</initial-state>
                            </properties>
                        </behavior-instance>
                        <behavior-instance type="Pathfinding">
                            <properties>
                                <cell-size>16</cell-size>
                                <cell-border>0</cell-border>
                                <obstacles>Solids</obstacles>
                                <max-speed>300</max-speed>
                                <acceleration>1000</acceleration>
                                <deceleration>2000</deceleration>
                                <rotate-speed>135</rotate-speed>
                                <rotate-object>No</rotate-object>
                                <diagonals>Enabled</diagonals>
                                <initial-state>Enabled</initial-state>
                            </properties>
                        </behavior-instance>
                        <behavior-instance type="Flash" />
                    </behavior-instances>
                    <blend-mode>0</blend-mode>
                    <effect-fallback>0</effect-fallback>
                    <world>
                        <x>770</x>
                        <y>220</y>
                        <z>0</z>
                        <width>32</width>
                        <height>32</height>
                        <depth>0</depth>
                        <hotspotX>0.5</hotspotX>
                        <hotspotY>0.5</hotspotY>
                        <angle>0</angle>
                        <opacity>1</opacity>
                    </world>
                </instance>
                <instance type="Enemy" uid="88">
                    <properties>
                        <initial-visibility>Visible</initial-visibility>
                        <initial-animation>Default</initial-animation>
                        <initial-frame>0</initial-frame>
                        <collisions>Enabled</collisions>
                    </properties>
                    <instance-variables>
                        <StepNum>1</StepNum>
                        <Alerted>false</Alerted>
                        <alertCooldown>0</alertCooldown>
                        <hasLineOfSight>false</hasLineOfSight>
                    </instance-variables>
                    <behavior-instances>
                        <behavior-instance type="LineOfSight">
                            <properties>
                                <obstacles>Solids</obstacles>
                                <range>200</range>
                                <cone-of-view>30</cone-of-view>
                                <use-collision-cells>Yes</use-collision-cells>
                            </properties>
                        </behavior-instance>
                        <behavior-instance type="Solid">
                            <properties>
                                <initial-state>Enabled</initial-state>
                            </properties>
                        </behavior-instance>
                        <behavior-instance type="Pathfinding">
                            <properties>
                                <cell-size>16</cell-size>
                                <cell-border>0</cell-border>
                                <obstacles>Solids</obstacles>
                                <max-speed>300</max-speed>
                                <acceleration>1000</acceleration>
                                <deceleration>2000</deceleration>
                                <rotate-speed>135</rotate-speed>
                                <rotate-object>No</rotate-object>
                                <diagonals>Enabled</diagonals>
                                <initial-state>Enabled</initial-state>
                            </properties>
                        </behavior-instance>
                        <behavior-instance type="Flash" />
                    </behavior-instances>
                    <blend-mode>0</blend-mode>
                    <effect-fallback>0</effect-fallback>
                    <world>
                        <x>424</x>
                        <y>511</y>
                        <z>0</z>
                        <width>32</width>
                        <height>32</height>
                        <depth>0</depth>
                        <hotspotX>0.5</hotspotX>
                        <hotspotY>0.5</hotspotY>
                        <angle>0</angle>
                        <opacity>1</opacity>
                    </world>
                </instance>
                <instance type="Enemy" uid="92">
                    <properties>
                        <initial-visibility>Visible</initial-visibility>
                        <initial-animation>Default</initial-animation>
                        <initial-frame>0</initial-frame>
                        <collisions>Enabled</collisions>
                    </properties>
                    <instance-variables>
                        <StepNum>1</StepNum>
                        <Alerted>false</Alerted>
                        <alertCooldown>0</alertCooldown>
                        <hasLineOfSight>false</hasLineOfSight>
                    </instance-variables>
                    <behavior-instances>
                        <behavior-instance type="LineOfSight">
                            <properties>
                                <obstacles>Solids</obstacles>
                                <range>200</range>
                                <cone-of-view>30</cone-of-view>
                                <use-collision-cells>Yes</use-collision-cells>
                            </properties>
                        </behavior-instance>
                        <behavior-instance type="Solid">
                            <properties>
                                <initial-state>Enabled</initial-state>
                            </properties>
                        </behavior-instance>
                        <behavior-instance type="Pathfinding">
                            <properties>
                                <cell-size>16</cell-size>
                                <cell-border>0</cell-border>
                                <obstacles>Solids</obstacles>
                                <max-speed>300</max-speed>
                                <acceleration>1000</acceleration>
                                <deceleration>2000</deceleration>
                                <rotate-speed>135</rotate-speed>
                                <rotate-object>No</rotate-object>
                                <diagonals>Enabled</diagonals>
                                <initial-state>Enabled</initial-state>
                            </properties>
                        </behavior-instance>
                        <behavior-instance type="Flash" />
                    </behavior-instances>
                    <blend-mode>0</blend-mode>
                    <effect-fallback>0</effect-fallback>
                    <world>
                        <x>858</x>
                        <y>59</y>
                        <z>0</z>
                        <width>32</width>
                        <height>32</height>
                        <depth>0</depth>
                        <hotspotX>0.5</hotspotX>
                        <hotspotY>0.5</hotspotY>
                        <angle>0</angle>
                        <opacity>1</opacity>
                    </world>
                </instance>
                <instance type="Enemy" uid="101">
                    <properties>
                        <initial-visibility>Visible</initial-visibility>
                        <initial-animation>Default</initial-animation>
                        <initial-frame>0</initial-frame>
                        <collisions>Enabled</collisions>
                    </properties>
                    <instance-variables>
                        <StepNum>1</StepNum>
                        <Alerted>false</Alerted>
                        <alertCooldown>0</alertCooldown>
                        <hasLineOfSight>false</hasLineOfSight>
                    </instance-variables>
                    <behavior-instances>
                        <behavior-instance type="LineOfSight">
                            <properties>
                                <obstacles>Solids</obstacles>
                                <range>200</range>
                                <cone-of-view>30</cone-of-view>
                                <use-collision-cells>Yes</use-collision-cells>
                            </properties>
                        </behavior-instance>
                        <behavior-instance type="Solid">
                            <properties>
                                <initial-state>Enabled</initial-state>
                            </properties>
                        </behavior-instance>
                        <behavior-instance type="Pathfinding">
                            <properties>
                                <cell-size>16</cell-size>
                                <cell-border>0</cell-border>
                                <obstacles>Solids</obstacles>
                                <max-speed>300</max-speed>
                                <acceleration>1000</acceleration>
                                <deceleration>2000</deceleration>
                                <rotate-speed>135</rotate-speed>
                                <rotate-object>No</rotate-object>
                                <diagonals>Enabled</diagonals>
                                <initial-state>Enabled</initial-state>
                            </properties>
                        </behavior-instance>
                        <behavior-instance type="Flash" />
                    </behavior-instances>
                    <blend-mode>0</blend-mode>
                    <effect-fallback>0</effect-fallback>
                    <world>
                        <x>325</x>
                        <y>374</y>
                        <z>0</z>
                        <width>32</width>
                        <height>32</height>
                        <depth>0</depth>
                        <hotspotX>0.5</hotspotX>
                        <hotspotY>0.5</hotspotY>
                        <angle>0</angle>
                        <opacity>1</opacity>
                    </world>
                </instance>
            </instances>
            <effects />
        </layer>
        <layer name="Light" sid="185293046825655">
            <initially-visible>1</initially-visible>
            <background-color>255,255,255</background-color>
            <transparent>1</transparent>
            <parallax>
                <x>1</x>
                <y>1</y>
            </parallax>
            <zoom-rate>1</zoom-rate>
            <opacity>1</opacity>
            <force-own-texture>0</force-own-texture>
            <global>0</global>
            <use-render-cells>0</use-render-cells>
            <blend-mode>0</blend-mode>
            <effect-fallback>0</effect-fallback>
            <instances>
                <instance type="HorizontalWall" uid="94">
                    <properties>
                        <initial-visibility>Visible</initial-visibility>
                        <initial-animation>Default</initial-animation>
                        <initial-frame>0</initial-frame>
                        <collisions>Enabled</collisions>
                    </properties>
                    <behavior-instances>
                        <behavior-instance type="Solid">
                            <properties>
                                <initial-state>Enabled</initial-state>
                            </properties>
                        </behavior-instance>
                        <behavior-instance type="ShadowCaster">
                            <properties>
                                <initial-state>Enabled</initial-state>
                                <height>100</height>
                                <tag></tag>
                            </properties>
                        </behavior-instance>
                    </behavior-instances>
                    <blend-mode>0</blend-mode>
                    <effect-fallback>0</effect-fallback>
                    <world>
                        <x>1731</x>
                        <y>343</y>
                        <z>0</z>
                        <width>32</width>
                        <height>10</height>
                        <depth>0</depth>
                        <hotspotX>0.5</hotspotX>
                        <hotspotY>0.5</hotspotY>
                        <angle>0</angle>
                        <opacity>1</opacity>
                    </world>
                </instance>
                <instance type="Level3Map" uid="60">
                    <properties>
                        <initial-visibility>Visible</initial-visibility>
                        <tile-width>32</tile-width>
                        <tile-height>32</tile-height>
                        <tile-x-offset>0</tile-x-offset>
                        <tile-y-offset>0</tile-y-offset>
                        <tile-x-spacing>0</tile-x-spacing>
                        <tile-y-spacing>0</tile-y-spacing>
                        <seamless-mode>On</seamless-mode>
                    </properties>
                    <behavior-instances>
                        <behavior-instance type="Solid">
                            <properties>
                                <initial-state>Enabled</initial-state>
                            </properties>
                        </behavior-instance>
                        <behavior-instance type="ShadowCaster">
                            <properties>
                                <initial-state>Enabled</initial-state>
                                <height>100</height>
                                <tag></tag>
                            </properties>
                        </behavior-instance>
                    </behavior-instances>
                    <blend-mode>0</blend-mode>
                    <effect-fallback>0</effect-fallback>
                    <world>
                        <x>1</x>
                        <y>3</y>
                        <z>0</z>
                        <width>1708</width>
                        <height>960</height>
                        <depth>0</depth>
                        <hotspotX>0</hotspotX>
                        <hotspotY>0</hotspotY>
                        <opacity>1</opacity>
                    </world>
                    <tilemap-data>
                        <width>53</width>
                        <height>30</height>
                        <max-width>53</max-width>
                        <max-height>30</max-height>
                        <data>124,124,92,92,93,93,93,93,93,93,93,93,125,93,93,93,93,93,93,93,93,93,93,93,93,93,93,93,125,124,124,125,93,93,93,125,94,94,94,94,94,94,94,-1,-1,-1,-1,-1,-1,-1,-1,-1,-1,-1,-1,-1,-1,519,93,125,124,-1,-1,-1,-1,-1,-1,-1,-1,-1,-1,-1,-1,94,-1,-1,-1,-1,-1,-1,-1,-1,-1,-1,-1,-1,-1,519,94,126,124,-1,-1,-1,-1,-1,-1,-1,-1,-1,-1,-1,-1,-1,94,-1,-1,-1,-1,-1,-1,-1,-1,-1,-1,-1,-1,-1,92,124,124,-1,-1,215,247,-1,-1,-1,-1,-1,-1,-1,-1,-1,94,94,-1,-1,-1,-1,94,94,94,94,94,94,94,94,93,125,124,-1,-1,216,248,-1,-1,-1,-1,-1,-1,-1,-1,-1,-1,-1,-1,-1,-1,-1,94,94,94,94,94,94,94,94,94,126,124,-1,-1,-1,-1,-1,-1,-1,-1,-1,-1,-1,-1,-1,-1,-1,-1,-1,-1,-1,94,94,94,94,94,94,94,94,92,124,124,-1,-1,-1,-1,-1,-1,94,94,94,94,94,-1,-1,-1,-1,-1,-1,-1,-1,94,94,94,94,94,94,94,94,93,125,124,-1,-1,-1,-1,94,94,94,-1,-1,-1,-1,-1,-1,-1,-1,-1,477,-1,-1,94,94,94,94,94,94,94,94,94,126,124,-1,-1,-1,-1,94,-1,-1,-1,-1,-1,-1,-1,-1,-1,-1,-1,477,-1,-1,94,477,477,477,477,477,477,477,92,124,124,124,-1,-1,-1,94,-1,-1,-1,-1,-1,-1,-1,-1,-1,-1,-1,477,-1,-1,94,-1,-1,-1,-1,-1,-1,-1,93,125,125,125,-1,-1,-1,94,94,94,94,94,94,94,94,94,94,94,94,94,94,94,94,-1,-1,-1,-1,-1,-1,-1,94,126,124,-1,-1,-1,-1,-1,-1,-1,-1,-1,-1,-1,-1,-1,-1,-1,-1,-1,-1,94,94,-1,-1,-1,-1,-1,-1,-1,92,124,125,-1,-1,-1,-1,-1,-1,-1,-1,-1,-1,-1,-1,-1,-1,-1,-1,-1,-1,94,94,-1,-1,-1,-1,-1,-1,-1,93,125,125,-1,-1,-1,-1,215,247,215,247,215,247,215,247,-1,-1,-1,-1,-1,-1,94,94,-1,-1,-1,94,-1,-1,-1,94,126,125,-1,-1,-1,-1,216,248,216,248,216,248,216,248,-1,-1,-1,-1,-1,-1,94,94,-1,-1,-1,94,-1,-1,-1,92,124,125,-1,-1,-1,-1,215,247,215,247,215,247,215,247,-1,-1,-1,-1,-1,-1,94,94,-1,-1,-1,94,-1,-1,-1,93,125,125,-1,-1,-1,-1,216,248,216,248,216,248,216,248,-1,-1,-1,-1,-1,-1,94,94,-1,-1,-1,94,126,94,126,94,126,125,-1,-1,-1,-1,-1,-1,-1,-1,-1,-1,-1,-1,-1,-1,-1,-1,-1,-1,94,94,-1,-1,-1,-1,-1,-1,-1,-1,92,125,-1,-1,-1,-1,-1,-1,-1,-1,-1,-1,-1,-1,-1,-1,-1,-1,-1,-1,94,94,-1,-1,-1,-1,-1,-1,-1,-1,93,125,-1,-1,-1,-1,-1,-1,-1,-1,-1,-1,-1,-1,94,94,94,-1,-1,-1,94,94,-1,-1,-1,-1,-1,-1,-1,-1,92,92,124,-1,-1,-1,-1,-1,-1,-1,-1,-1,-1,-1,94,94,94,-1,-1,-1,94,-1,-1,-1,-1,-1,-1,-1,-1,-1,93,92,124,-1,-1,-1,94,94,94,94,94,94,-1,-1,94,94,94,-1,-1,-1,94,-1,-1,-1,22,22,22,-1,-1,-1,92,92,124,-1,-1,-1,94,-1,-1,-1,27,-1,-1,-1,94,94,94,-1,-1,-1,94,-1,-1,-1,22,22,22,-1,-1,-1,93,93,125,-1,-1,-1,94,-1,-1,-1,27,-1,-1,-1,94,94,94,-1,-1,-1,94,-1,-1,-1,22,22,22,-1,-1,-1,92,124,-1,-1,-1,-1,94,-1,-1,-1,27,-1,-1,-1,94,94,94,-1,-1,-1,94,-1,-1,-1,22,22,22,-1,-1,-1,93,125,-1,-1,-1,-1,94,-1,-1,-1,27,-1,-1,-1,94,94,94,-1,-1,-1,94,-1,-1,-1,22,22,22,-1,-1,-1,92,125,-1,-1,-1,-1,94,-1,-1,-1,27,-1,-1,-1,94,94,94,-1,-1,-1,94,-1,-1,-1,-1,-1,-1,-1,-1,-1,93,125,-1,-1,-1,-1,94,-1,-1,-1,27,94,94,94,94,94,94,-1,-1,-1,94,94,-1,-1,-1,-1,-1,-1,-1,-1,92,125,-1,-1,215,-1,94,-1,-1,-1,-1,-1,-1,-1,-1,-1,-1,-1,-1,-1,-1,94,-1,-1,-1,-1,-1,-1,-1,-1,93,125,-1,-1,216,-1,94,-1,-1,-1,-1,-1,-1,-1,-1,-1,-1,-1,-1,-1,-1,94,-1,-1,-1,-1,-1,-1,-1,-1,92,125,-1,-1,-1,-1,94,-1,-1,-1,-1,-1,-1,-1,-1,-1,-1,-1,-1,-1,-1,94,-1,-1,-1,-1,-1,-1,-1,-1,93,124,-1,-1,-1,-1,94,94,94,94,94,94,94,94,94,94,94,-1,-1,-1,-1,94,-1,-1,-1,94,126,94,126,92,124,125,-1,-1,-1,-1,94,94,94,94,94,94,94,94,94,94,94,-1,-1,-1,-1,94,-1,-1,-1,-1,-1,-1,-1,93,125,125,-1,-1,-1,-1,94,94,94,94,94,94,94,94,94,94,94,-1,-1,-1,-1,94,-1,-1,-1,-1,-1,-1,-1,94,126,125,-1,-1,-1,-1,94,94,94,94,94,94,94,94,94,94,94,-1,-1,-1,-1,94,-1,-1,-1,-1,-1,-1,-1,92,124,125,-1,-1,-1,-1,94,94,94,94,94,94,94,94,94,94,94,-1,-1,-1,-1,94,94,94,94,-1,-1,-1,-1,93,125,125,-1,215,-1,-1,94,94,-1,-1,-1,-1,-1,-1,-1,-1,-1,-1,-1,-1,-1,-1,-1,-1,94,-1,-1,-1,-1,94,126,125,-1,216,-1,-1,94,-1,-1,-1,-1,-1,-1,-1,-1,-1,-1,-1,-1,-1,-1,-1,-1,94,-1,-1,-1,-1,-1,94,126,125,-1,-1,-1,-1,94,-1,-1,-1,-1,-1,-1,-1,-1,-1,-1,-1,-1,-1,-1,-1,94,-1,-1,-1,-1,-1,-1,92,124,125,-1,-1,-1,-1,94,-1,-1,215,247,-1,-1,-1,-1,-1,-1,-1,-1,-1,-1,-1,94,-1,-1,-1,-1,-1,-1,93,125,125,-1,-1,-1,-1,94,-1,-1,216,248,-1,-1,-1,-1,-1,-1,-1,-1,-1,-1,-1,94,-1,-1,-1,-1,-1,-1,94,126,125,-1,-1,-1,-1,94,-1,-1,215,247,-1,-1,94,94,94,94,94,-1,-1,-1,-1,94,-1,-1,-1,22,-1,-1,92,124,125,-1,-1,-1,-1,94,-1,-1,216,248,-1,-1,94,94,94,94,94,-1,-1,-1,-1,-1,-1,-1,-1,22,-1,-1,93,125,125,124,-1,-1,-1,94,-1,-1,-1,-1,-1,-1,94,94,94,94,94,-1,-1,-1,-1,-1,-1,-1,-1,22,-1,-1,94,126,125,125,-1,-1,-1,94,-1,-1,-1,-1,-1,-1,94,94,94,94,94,-1,-1,-1,-1,-1,-1,-1,-1,22,-1,-1,92,124,93,125,-1,-1,-1,94,94,-1,-1,-1,-1,-1,94,94,94,94,94,94,94,94,94,94,-1,-1,-1,22,-1,-1,93,125,93,125,-1,-1,-1,-1,94,-1,-1,-1,-1,-1,94,94,-1,-1,-1,-1,-1,-1,-1,-1,-1,-1,-1,-1,-1,-1,94,126,125,-1,-1,-1,-1,-1,94,-1,-1,-1,-1,-1,94,94,-1,-1,-1,-1,-1,-1,-1,-1,-1,-1,-1,-1,-1,-1,92,124,125,124,-1,-1,-1,-1,94,-1,-1,-1,-1,-1,94,94,-1,-1,-1,375,375,375,-1,-1,-1,-1,-1,-1,-1,-1,93,125,125,125,-1,-1,-1,-1,94,-1,-1,-1,-1,-1,94,94,-1,-1,-1,-1,-1,-1,-1,-1,-1,-1,-1,-1,-1,-1,92,124,93,125,-1,-1,-1,-1,94,-1,-1,-1,-1,-1,92,92,124,-1,-1,-1,-1,-1,-1,-1,-1,124,124,124,124,124,92,124,93,125,124,124,124,124,124,124,124,92,92,92,93,93,125,124,124,124,124,124,124,124,125,125,125,125,125,125,92,124</data>
                    </tilemap-data>
                </instance>
                <instance type="ShadowLight" uid="63">
                    <properties>
                        <light-height>1</light-height>
                        <light-radius>0</light-radius>
                        <cast-from>All</cast-from>
                        <tag></tag>
                    </properties>
                    <blend-mode>0</blend-mode>
                    <effect-fallback>0</effect-fallback>
                    <world>
                        <x>419</x>
                        <y>849</y>
                        <z>0</z>
                        <width>50</width>
                        <height>50</height>
                        <depth>0</depth>
                        <hotspotX>0.5</hotspotX>
                        <hotspotY>0.5</hotspotY>
                        <opacity>0.899999976</opacity>
                    </world>
                </instance>
                <instance type="VerticalWall" uid="95">
                    <properties>
                        <initial-visibility>Visible</initial-visibility>
                        <initial-animation>Default</initial-animation>
                        <initial-frame>0</initial-frame>
                        <collisions>Enabled</collisions>
                    </properties>
                    <behavior-instances>
                        <behavior-instance type="ShadowCaster">
                            <properties>
                                <initial-state>Enabled</initial-state>
                                <height>100</height>
                                <tag></tag>
                            </properties>
                        </behavior-instance>
                        <behavior-instance type="Solid">
                            <properties>
                                <initial-state>Enabled</initial-state>
                            </properties>
                        </behavior-instance>
                    </behavior-instances>
                    <blend-mode>0</blend-mode>
                    <effect-fallback>0</effect-fallback>
                    <world>
                        <x>1736</x>
                        <y>448</y>
                        <z>0</z>
                        <width>10</width>
                        <height>32</height>
                        <depth>0</depth>
                        <hotspotX>0.5</hotspotX>
                        <hotspotY>0.5</hotspotY>
                        <angle>0</angle>
                        <opacity>1</opacity>
                    </world>
                </instance>
            </instances>
            <effects />
        </layer>
    </layers>
    <nonworld-instances />
    <effects />
</c2layout>
